Lab5/Part1/alu.v
// This module is the top-level module for testing the ALU module
module testbed;

    // Declaring the input and output signals for the testbed
    reg [7:0] DATA1_test, DATA2_test;
    reg [2:0] SELECT_test;
    wire [7:0] RESULT_test;

    // Instantiating the ALU module and connecting its ports to the testbed signals
    ALU alu_t(DATA1_test,DATA2_test,SELECT_test,RESULT_test);

    // Defining the initial block for simulation
    initial
    begin
        // Printing the values of the signals using $monitor system task
        $monitor("TIME = %g  DATA1 = %b, DATA2 = %b, SELECT = %b, RESULT = %b", $time, DATA1_test, DATA2_test, SELECT_test, RESULT_test);
        
        // Creating a VCD file for waveform viewing using $dumpfile system task
        $dumpfile("wavedata_ALU.vcd");
        
        // Adding signals to be dumped to the VCD file using $dumpvars system task
        $dumpvars(0, testbed);

        // Set initial values for inputs and test ALU operations
        DATA1_test = 1;
        DATA2_test = 2;
        SELECT_test = 0;

        #6
        DATA1_test = 3;
        DATA2_test = 4;
        SELECT_test = 1;

        #7
        DATA1_test = 4;
        DATA2_test = 5;
        SELECT_test = 2;

        #6
        DATA1_test = 6;
        DATA2_test = 7;
        SELECT_test = 3;

        #6
        $finish;    // Finishing the simulation
    end
 endmodule


// This module performs addition of two 8-bit data inputs
module ADD(DATA1,DATA2,RESULT);
    input [7:0] DATA1, DATA2;
    output [7:0] RESULT;

    // Assigning the sum of DATA1 and DATA2 to RESULT after a delay of 2 time units
    assign #2 RESULT = DATA2 + DATA1;
endmodule


// This module forwards the 8-bit data input to the output without any operation
module FORWARD(DATA2,RESULT);
    input [7:0] DATA2;
    output [7:0] RESULT;
    
    // Assigning the input data to the output after a delay of 1 time unit
    assign #1 RESULT = DATA2;
endmodule


// This module performs bitwise AND operation on two 8-bit data inputs
module AND(DATA1,DATA2,RESULT);
    input [7:0] DATA1, DATA2;
    output [7:0] RESULT;

    //assigning the result to output after a delay of 1 time unit
    assign #1 RESULT = DATA2 & DATA1;
endmodule


// This module performs bitwise OR operation on two 8-bit data inputs
module OR(DATA1,DATA2,RESULT);
    input [7:0] DATA1, DATA2;
    output [7:0] RESULT;

    //assigning the result to output after a delay of 1 time unit
    assign #1 RESULT = DATA2 | DATA1;
endmodule


// ALU module definition
module ALU(DATA1,DATA2,SELECT,RESULT);

    // Declaring the input and output
    input [7:0] DATA1, DATA2;
    input [2:0] SELECT;
    reg [7:0] RESULT;
    output [7:0] RESULT;
    wire [7:0] OUTPUT_add, OUTPUT_forward, OUTPUT_or, OUTPUT_and;

    // Instantiating the FORWARD, ADD, AND, and OR modules with necessary inputs and outputs
    FORWARD forward_(DATA2, OUTPUT_forward);
    ADD add_(DATA1, DATA2, OUTPUT_add);
    AND and_(DATA1, DATA2, OUTPUT_and);
    OR or_(DATA1, DATA2, OUTPUT_or);

    // Triggering when any of the input signals or any of the output wires changes
    always @ (OUTPUT_forward, OUTPUT_add, OUTPUT_and, OUTPUT_or, SELECT)
	begin
		case (SELECT) // SELECT input to select which module output to assign to the RESULT register		

			3'b000 :	RESULT = OUTPUT_forward;  // if SELECT is 000, forward the DATA2 input to the RESULT
			3'b001 :	RESULT = OUTPUT_add;      // if SELECT is 001, assign the output of the adder to the RESULT
			3'b010 :	RESULT = OUTPUT_and;      // if SELECT is 010, assign the output of the bitwise AND to the RESULT
			3'b011 :	RESULT = OUTPUT_or;       // if SELECT is 011, assign the output of the bitwise OR to the RESULT		
			
		endcase
	end
    
endmodule

Lab5/Part1/ALU.vcd
$date
	Mon May 08 21:39:39 2023
$end
$version
	Icarus Verilog
$end
$timescale
	1s
$end
$scope module testbed $end
$var wire 8 ! RESULT_test [7:0] $end
$var reg 8 " DATA1_test [7:0] $end
$var reg 8 # DATA2_test [7:0] $end
$var reg 3 $ SELECT_test [2:0] $end
$scope module alu_t $end
$var wire 8 % DATA1 [7:0] $end
$var wire 8 & DATA2 [7:0] $end
$var wire 3 ' SELECT [2:0] $end
$var wire 8 ( OUTPUT_or [7:0] $end
$var wire 8 ) OUTPUT_forward [7:0] $end
$var wire 8 * OUTPUT_and [7:0] $end
$var wire 8 + OUTPUT_add [7:0] $end
$var reg 8 , RESULT [7:0] $end
$scope module add_ $end
$var wire 8 - DATA1 [7:0] $end
$var wire 8 . DATA2 [7:0] $end
$var wire 8 / RESULT [7:0] $end
$upscope $end
$scope module and_ $end
$var wire 8 0 DATA1 [7:0] $end
$var wire 8 1 DATA2 [7:0] $end
$var wire 8 2 RESULT [7:0] $end
$upscope $end
$scope module forward_ $end
$var wire 8 3 DATA2 [7:0] $end
$var wire 8 4 RESULT [7:0] $end
$upscope $end
$scope module or_ $end
$var wire 8 5 DATA1 [7:0] $end
$var wire 8 6 DATA2 [7:0] $end
$var wire 8 7 RESULT [7:0] $end
$upscope $end
$upscope $end
$upscope $end
$enddefinitions $end
$comment Show the parameter values. $end
$dumpall
$end
#0
$dumpvars
bx 7
b10 6
b1 5
bx 4
b10 3
bx 2
b10 1
b1 0
bx /
b10 .
b1 -
bx ,
bx +
bx *
bx )
bx (
b0 '
b10 &
b1 %
b0 $
b10 #
b1 "
bx !
$end
#1
b10 !
b10 ,
b11 (
b11 7
b0 *
b0 2
b10 )
b10 4
#2
b11 +
b11 /
#6
b11 !
b11 ,
b1 $
b1 '
b100 #
b100 &
b100 .
b100 1
b100 3
b100 6
b11 "
b11 %
b11 -
b11 0
b11 5
#7
b111 (
b111 7
b100 )
b100 4
#8
b111 !
b111 ,
b111 +
b111 /
#13
b0 !
b0 ,
b10 $
b10 '
b101 #
b101 &
b101 .
b101 1
b101 3
b101 6
b100 "
b100 %
b100 -
b100 0
b100 5
#14
b100 !
b100 ,
b100 *
b100 2
b101 (
b101 7
b101 )
b101 4
#15
b1001 +
b1001 /
#19
b101 !
b101 ,
b11 $
b11 '
b111 #
b111 &
b111 .
b111 1
b111 3
b111 6
b110 "
b110 %
b110 -
b110 0
b110 5
#20
b111 !
b111 ,
b110 *
b110 2
b111 (
b111 7
b111 )
b111 4
#21
b1101 +
b1101 /
